dask2py.py
dask2py-0.0.1.dist-info/WHEEL
dask2py-0.0.1.dist-info/METADATA
dask2py-0.0.1.dist-info/RECORD
