Metadata-Version: 1.2
Name: dask2py
Version: 0.0.1
Summary: Print executable code from a dask graph.
Home-page: http://github.com/cesium-ml/dask2py
License: UNKNOWN
Author: Brett Naul
Author-email: brettnaul@gmail.com
